psutil_demo/__init__.py
psutil_demo/main.py
psutil_demo-0.1.2.dist-info/LICENSE
psutil_demo-0.1.2.dist-info/METADATA
psutil_demo-0.1.2.dist-info/WHEEL
psutil_demo-0.1.2.dist-info/top_level.txt
psutil_demo-0.1.2.dist-info/RECORD
